{
  "name": "Adventure World Demo",
  "background": "Day",
  "rules": {
    "max_guests": 120,
    "spawn_rate": 1.2,
    "target_fps": 24
  },
  "rides": [
    {
      "type": "PirateShip",
      "position": {
        "x": 0,
        "y": 10
      },
      "max_capacity": 16,
      "ride_time": 30
    },
    {
      "type": "PirateShip",
      "position": {
        "x": 0,
        "y": 20
      },
      "max_capacity": 16,
      "ride_time": 30
    },
    {
      "type": "PirateShip",
      "position": {
        "x": 0,
        "y": 30
      },
      "max_capacity": 16,
      "ride_time": 30
    },
    {
      "type": "PirateShip",
      "position": {
        "x": 0,
        "y": 40
      },
      "max_capacity": 16,
      "ride_time": 30
    },
    {
      "type": "PirateShip",
      "position": {
        "x": 0,
        "y": 50
      },
      "max_capacity": 16,
      "ride_time": 30
    },
    {
      "type": "FerrisWheel",
      "position": {
        "x": 0,
        "y": 60
      },
      "max_capacity": 16,
      "ride_time": 30
    },
    {
      "type": "DropTower",
      "position": {
        "x": 10,
        "y": 10
      },
      "max_capacity": 16,
      "ride_time": 30
    }
  ]
}
